{"_type":"export","__export_format":4,"__export_date":"2021-07-04T20:49:26.837Z","__export_source":"insomnia.desktop.app:v2021.4.0","resources":[{"_id":"req_a6b945ffba854b749225b468a8661624","parentId":"fld_824c31713af54fd8827e5089cc02727e","modified":1625419711428,"created":1625415979559,"url":"{{ _.host }}/api/admin/users","name":"Create","description":"","method":"POST","body":{"mimeType":"application/json","text":"{\n\t\"login\": \"testUser1111211\",\n\t\"password\": \"testUser\",\n\t\"first_name\": \"test\",\n\t\"last_name\": \"user\",\n\t\"telegram_id\": \"123\"\n}"},"parameters":[],"headers":[{"name":"Content-Type","value":"application/json","id":"pair_4fe7847283d3461daf1c808d4f8126ef"},{"id":"pair_9ba3519c2b2f410792b062229d2ef197","name":"accept","value":"application/json","description":"","disabled":false}],"authentication":{"type":"bearer","token":"{{ _.token }}"},"metaSortKey":-1625415979559,"isPrivate":false,"settingStoreCookies":true,"settingSendCookies":true,"settingDisableRenderRequestBody":false,"settingEncodeUrl":true,"settingRebuildPath":true,"settingFollowRedirects":"global","_type":"request"},{"_id":"fld_824c31713af54fd8827e5089cc02727e","parentId":"fld_79977c10a265486da370858defd6fed8","modified":1625415963118,"created":1625415963118,"name":"Users","description":"","environment":{},"environmentPropertyOrder":null,"metaSortKey":-1625415963118,"_type":"request_group"},{"_id":"fld_79977c10a265486da370858defd6fed8","parentId":"wrk_429799ac0f7b42029c6a8f1ceeb65914","modified":1625406936763,"created":1625406936763,"name":"Admin","description":"","environment":{},"environmentPropertyOrder":null,"metaSortKey":-1625406936763,"_type":"request_group"},{"_id":"wrk_429799ac0f7b42029c6a8f1ceeb65914","parentId":null,"modified":1625324596512,"created":1625324596512,"name":"Laravel-template","description":"","scope":"collection","_type":"workspace"},{"_id":"req_83bbd89517994f0184918437461b1e83","parentId":"fld_824c31713af54fd8827e5089cc02727e","modified":1625419665482,"created":1625419654514,"url":"{{ _.host }}/api/admin/users","name":"Index","description":"","method":"GET","body":{"mimeType":"application/json","text":""},"parameters":[],"headers":[{"name":"Content-Type","value":"application/json","id":"pair_4fe7847283d3461daf1c808d4f8126ef"},{"id":"pair_9ba3519c2b2f410792b062229d2ef197","name":"accept","value":"application/json","description":"","disabled":false}],"authentication":{"type":"bearer","token":"{{ _.token }}"},"metaSortKey":-1625413720998.5,"isPrivate":false,"settingStoreCookies":true,"settingSendCookies":true,"settingDisableRenderRequestBody":false,"settingEncodeUrl":true,"settingRebuildPath":true,"settingFollowRedirects":"global","_type":"request"},{"_id":"req_bace8fb1131c4dfc93994f4a00bcd694","parentId":"fld_824c31713af54fd8827e5089cc02727e","modified":1625421404428,"created":1625419287008,"url":"{{ _.host }}/api/admin/users/1","name":"Update","description":"","method":"PUT","body":{"mimeType":"application/json","text":"{\n\t\"login\": \"admin\",\n\t\"password\": \"admin\",\n\t\"first_name\": \"test\",\n\t\"last_name\": \"user\",\n\t\"telegram_id\": \"123\"\n}"},"parameters":[],"headers":[{"name":"Content-Type","value":"application/json","id":"pair_4fe7847283d3461daf1c808d4f8126ef"},{"id":"pair_9ba3519c2b2f410792b062229d2ef197","name":"accept","value":"application/json","description":"","disabled":false}],"authentication":{"type":"bearer","token":"{{ _.token }}"},"metaSortKey":-1625411462438,"isPrivate":false,"settingStoreCookies":true,"settingSendCookies":true,"settingDisableRenderRequestBody":false,"settingEncodeUrl":true,"settingRebuildPath":true,"settingFollowRedirects":"global","_type":"request"},{"_id":"req_0a7db02adc6f4c139faf854dc86c7a1f","parentId":"fld_79977c10a265486da370858defd6fed8","modified":1625406976594,"created":1625406945265,"url":"{{ _.host }}/api/admin/roles","name":"Roles","description":"","method":"GET","body":{},"parameters":[],"headers":[],"authentication":{"type":"bearer","token":"{{ _.token }}"},"metaSortKey":-1625406945317,"isPrivate":false,"settingStoreCookies":true,"settingSendCookies":true,"settingDisableRenderRequestBody":false,"settingEncodeUrl":true,"settingRebuildPath":true,"settingFollowRedirects":"global","_type":"request"},{"_id":"req_5a2a20465b8c41c4863e07188704c69a","parentId":"fld_0d768173c20247cb9c56cd94e8afddec","modified":1625406754847,"created":1625402009196,"url":"{{ _.host }}/api/auth/login","name":"Login","description":"","method":"POST","body":{"mimeType":"application/json","text":"{\n\t\"login\": \"admin\",\n\t\"password\": \"admin\"\n}"},"parameters":[],"headers":[{"id":"pair_9b354e46d62c4b7c94311d9111462a07","name":"accept","value":"application/json","description":""},{"name":"Content-Type","value":"application/json","id":"pair_fbc4213db29d41b89f537d390ce59218"}],"authentication":{"type":"bearer","token":"{{ _.token }}"},"metaSortKey":-1625402009196,"isPrivate":false,"settingStoreCookies":true,"settingSendCookies":true,"settingDisableRenderRequestBody":false,"settingEncodeUrl":true,"settingRebuildPath":true,"settingFollowRedirects":"global","_type":"request"},{"_id":"fld_0d768173c20247cb9c56cd94e8afddec","parentId":"wrk_429799ac0f7b42029c6a8f1ceeb65914","modified":1625404879520,"created":1625404879520,"name":"Auth","description":"","environment":{},"environmentPropertyOrder":null,"metaSortKey":-1625404879520,"_type":"request_group"},{"_id":"req_7410d04f2dc6422284700954d608e4ac","parentId":"fld_561eff1ce0594a38ac3185652c486cc9","modified":1625406190909,"created":1625404867387,"url":"{{ _.host }}/api/me","name":"Me","description":"","method":"GET","body":{},"parameters":[],"headers":[{"id":"pair_9b354e46d62c4b7c94311d9111462a07","name":"accept","value":"application/json","description":""}],"authentication":{"type":"bearer","token":"{{ _.token }}"},"metaSortKey":-1625273395429.5,"isPrivate":false,"settingStoreCookies":true,"settingSendCookies":true,"settingDisableRenderRequestBody":false,"settingEncodeUrl":true,"settingRebuildPath":true,"settingFollowRedirects":"global","_type":"request"},{"_id":"fld_561eff1ce0594a38ac3185652c486cc9","parentId":"wrk_429799ac0f7b42029c6a8f1ceeb65914","modified":1625402005490,"created":1625402005490,"name":"Profile","description":"","environment":{},"environmentPropertyOrder":null,"metaSortKey":-1625402005490,"_type":"request_group"},{"_id":"env_883dfe35867b64b4f60ef3e1a6c95dbd6722e28b","parentId":"wrk_429799ac0f7b42029c6a8f1ceeb65914","modified":1625324597096,"created":1625324597096,"name":"Base Environment","data":{},"dataPropertyOrder":null,"color":null,"isPrivate":false,"metaSortKey":1625324597096,"_type":"environment"},{"_id":"jar_883dfe35867b64b4f60ef3e1a6c95dbd6722e28b","parentId":"wrk_429799ac0f7b42029c6a8f1ceeb65914","modified":1625324597117,"created":1625324597117,"name":"Default Jar","cookies":[],"_type":"cookie_jar"},{"_id":"spc_b826dc01869e410d883c60a8b48b91d9","parentId":"wrk_429799ac0f7b42029c6a8f1ceeb65914","modified":1625324596523,"created":1625324596523,"fileName":"Laravel-template","contents":"","contentType":"yaml","_type":"api_spec"},{"_id":"env_24051dbe04bc48a38a89719daed2bf3b","parentId":"env_883dfe35867b64b4f60ef3e1a6c95dbd6722e28b","modified":1625416900596,"created":1625401949988,"name":"Local","data":{"token":"1|pVAskIkFmiv5CcPXs23wH0prtC8uP5N07qcCGaWR","host":"http://127.0.0.1:8000"},"dataPropertyOrder":{"&":["token","host"]},"color":null,"isPrivate":false,"metaSortKey":1625401949988,"_type":"environment"}]}